groupdocs/conversion/py.typed
aspose/pycore/py.typed
aspose/pycore/__init__.pyi
aspose/pyreflection/py.typed
aspose/pyreflection/__init__.pyi
aspose/pydrawing/py.typed
aspose/pydrawing/__init__.pyi
aspose/pydrawing/design.pyi
aspose/pydrawing/drawing2d.pyi
aspose/pydrawing/imaging.pyi
aspose/pydrawing/printing.pyi
aspose/pydrawing/text.pyi
groupdocs/conversion/__init__.pyi
groupdocs/conversion/caching/__init__.pyi
groupdocs/conversion/contracts/__init__.pyi
groupdocs/conversion/exceptions/__init__.pyi
groupdocs/conversion/filetypes/__init__.pyi
groupdocs/conversion/logging/__init__.pyi
groupdocs/conversion/options/__init__.pyi
groupdocs/conversion/options/convert/__init__.pyi
groupdocs/conversion/options/load/__init__.pyi
.__pyi_patched
groupdocs/__init__.py
groupdocs/conversion.cp310-win32.pyd
groupdocs/conversion.cp311-win32.pyd
groupdocs/conversion.cp312-win32.pyd
groupdocs/conversion.cp313-win32.pyd
groupdocs/conversion.cp35-win32.pyd
groupdocs/conversion.cp36-win32.pyd
groupdocs/conversion.cp37-win32.pyd
groupdocs/conversion.cp38-win32.pyd
groupdocs/conversion.cp39-win32.pyd
groupdocs/pycore.cp310-win32.pyd
groupdocs/pycore.cp311-win32.pyd
groupdocs/pycore.cp312-win32.pyd
groupdocs/pycore.cp313-win32.pyd
groupdocs/pycore.cp35-win32.pyd
groupdocs/pycore.cp36-win32.pyd
groupdocs/pycore.cp37-win32.pyd
groupdocs/pycore.cp38-win32.pyd
groupdocs/pycore.cp39-win32.pyd
groupdocs/pydrawing.cp310-win32.pyd
groupdocs/pydrawing.cp311-win32.pyd
groupdocs/pydrawing.cp312-win32.pyd
groupdocs/pydrawing.cp313-win32.pyd
groupdocs/pydrawing.cp35-win32.pyd
groupdocs/pydrawing.cp36-win32.pyd
groupdocs/pydrawing.cp37-win32.pyd
groupdocs/pydrawing.cp38-win32.pyd
groupdocs/pydrawing.cp39-win32.pyd
groupdocs/pygc.cp310-win32.pyd
groupdocs/pygc.cp311-win32.pyd
groupdocs/pygc.cp312-win32.pyd
groupdocs/pygc.cp313-win32.pyd
groupdocs/pygc.cp35-win32.pyd
groupdocs/pygc.cp36-win32.pyd
groupdocs/pygc.cp37-win32.pyd
groupdocs/pygc.cp38-win32.pyd
groupdocs/pygc.cp39-win32.pyd
groupdocs_conversion_net-25.12.dist-info/METADATA
groupdocs_conversion_net-25.12.dist-info/WHEEL
groupdocs_conversion_net-25.12.dist-info/entry_points.txt
groupdocs_conversion_net-25.12.dist-info/top_level.txt
groupdocs_conversion_net-25.12.dist-info/RECORD
