Metadata-Version: 2.1
Name: groupdocs-conversion-net
Version: 25.12
Summary: GroupDocs.Conversion for Python via .NET is a document conversion API that supports over 10,000 conversion pairs across popular formats and enables developers to easily convert files to various formats, such as PDF, HTML, JPG, or PNG. With this API, you can seamlessly convert a wide range of file types, including popular OpenDocument and Microsoft Office formats like DOCX, XLSX, and PPTX, as well as specialized CAD and graphic editor files like DWG, DXF, PSD, AI, and CDR. Supports Pytho
Home-page: https://products.groupdocs.com/conversion/python-net/
Author: GroupDocs
License: Other/Proprietary License
Keywords: conversion,convert,file,document,api,pdf,docx,xlsx,pptx,html,png,word,excel,powerpoint,visio,opendocument,photoshop
Platform: win32
Classifier: Operating System :: Microsoft :: Windows
Classifier: Operating System :: POSIX :: Linux
Classifier: Operating System :: Unix
Classifier: License :: Other/Proprietary License
Classifier: Programming Language :: Python
Classifier: Programming Language :: Python :: 3
Classifier: Programming Language :: Python :: 3 :: Only
Classifier: Programming Language :: Python :: 3.5
Classifier: Topic :: File Formats
Classifier: Topic :: Software Development :: Libraries
Classifier: Topic :: Utilities
Requires-Python: >=3.5,<3.14
